pystress/__init__.py
pystress/__main__.py
pystress/cli.py
pystress/http.py
pystress/logger.py
pystress/metrics.py
pystress/report.py
pystress/worker.py
pystress_no_gil-0.1.0.dist-info/licenses/LICENSE
pystress_no_gil-0.1.0.dist-info/METADATA
pystress_no_gil-0.1.0.dist-info/WHEEL
pystress_no_gil-0.1.0.dist-info/entry_points.txt
pystress_no_gil-0.1.0.dist-info/top_level.txt
pystress_no_gil-0.1.0.dist-info/RECORD
