Metadata-Version: 2.4
Name: pystress-no-gil
Version: 0.1.0
Summary: High-performance, free-threaded Python HTTP load tester with rich HTML reports and true parallelism
Author-email: Hammad Abbasi <hammad.ulhaq@empowerid.com>
Maintainer-email: Hammad Abbasi <hammad.ulhaq@empowerid.com>
License: MIT
Project-URL: Homepage, https://github.com/hammadabbasi/PyStress
Project-URL: Repository, https://github.com/hammadabbasi/PyStress.git
Project-URL: Issues, https://github.com/hammadabbasi/PyStress/issues
Project-URL: Documentation, https://github.com/hammadabbasi/PyStress#readme
Project-URL: Changelog, https://github.com/hammadabbasi/PyStress/blob/main/CHANGELOG.md
Keywords: load testing,performance,HTTP,benchmark,stress test,free-threaded,python 3.14,no-gil,parallel,benchmarking
Classifier: Development Status :: 3 - Alpha
Classifier: Intended Audience :: Developers
Classifier: License :: OSI Approved :: MIT License
Classifier: Programming Language :: Python
Classifier: Programming Language :: Python :: 3
Classifier: Programming Language :: Python :: 3 :: Only
Classifier: Programming Language :: Python :: 3.10
Classifier: Programming Language :: Python :: 3.11
Classifier: Programming Language :: Python :: 3.12
Classifier: Programming Language :: Python :: 3.14
Classifier: Topic :: Software Development :: Testing
Classifier: Topic :: Internet :: WWW/HTTP
Requires-Python: >=3.10
License-File: LICENSE
Requires-Dist: psutil>=5.9.0
Requires-Dist: urllib3>=2.0.0
Dynamic: license-file
